detectpii/__init__.py
detectpii/catalog/__init__.py
detectpii/catalog/bigquery_catalog.py
detectpii/catalog/hive_catalog.py
detectpii/catalog/postgres_catalog.py
detectpii/catalog/snowflake_catalog.py
detectpii/catalog/trino_catalog.py
detectpii/catalog/yugabyte_catalog.py
detectpii/common_regex/__init__.py
detectpii/detector/__init__.py
detectpii/detector/base.py~
detectpii/detector/column_name_regex.py
detectpii/detector/column_value_regex.py
detectpii/detector/english_column_name_regex.py
detectpii/detector/spanish_column_name_regex.py
detectpii/model.py
detectpii/pii_type.py
detectpii/pipeline/__init__.py
detectpii/pipeline/persistence.py
detectpii/pipeline/pii_detection.py
detectpii/resolver/__init__.py
detectpii/resolver/environment.py
detectpii/resolver/model.py
detectpii/resolver/plaintext.py
detectpii/scanner/__init__.py
detectpii/scanner/data.py
detectpii/scanner/metadata.py
detectpii/util.py
detectpii-0.1.8.dist-info/LICENSE
detectpii-0.1.8.dist-info/METADATA
detectpii-0.1.8.dist-info/WHEEL
detectpii-0.1.8.dist-info/RECORD
