Metadata-Version: 2.1
Name: detectpii
Version: 0.1.8
Summary: Detect PII columns in your database and warehouse
Home-page: https://github.com/thescalaguy/detectpii
Author: Fasih Khatib
Author-email: hellofasih.confound928@passinbox.com
Requires-Python: >=3.11,<4.0
Classifier: Programming Language :: Python :: 3
Classifier: Programming Language :: Python :: 3.11
Classifier: Programming Language :: Python :: 3.12
Provides-Extra: bigquery
Provides-Extra: hive
Provides-Extra: postgres
Provides-Extra: snowflake
Provides-Extra: trino
Provides-Extra: yugabyte
Requires-Dist: attrs (>=24.2.0,<25.0.0)
Requires-Dist: cattrs (>=23.2.3,<24.0.0)
Requires-Dist: google-cloud-bigquery (>=3.27.0,<4.0.0) ; extra == "bigquery"
Requires-Dist: psycopg2-binary (>=2.9.9,<3.0.0) ; extra == "postgres" or extra == "yugabyte"
Requires-Dist: pyhive[hive-pure-sasl] (>=0.7.0,<0.8.0) ; extra == "hive"
Requires-Dist: snowflake-sqlalchemy (>=1.6.1,<2.0.0) ; extra == "snowflake"
Requires-Dist: sqlalchemy (>=2.0.32,<3.0.0) ; extra == "hive" or extra == "postgres" or extra == "snowflake" or extra == "trino" or extra == "yugabyte"
Requires-Dist: tabulate (>=0.9.0,<0.10.0)
Requires-Dist: trino[sqlalchemy] (>=0.329.0,<0.330.0) ; extra == "trino"
Project-URL: Repository, https://github.com/thescalaguy/detectpii
